README.txt
setup.cfg
setup.py
docs/HISTORY.txt
indra/__init__.py
indra.util.egg-info/PKG-INFO
indra.util.egg-info/SOURCES.txt
indra.util.egg-info/dependency_links.txt
indra.util.egg-info/entry_points.txt
indra.util.egg-info/namespace_packages.txt
indra.util.egg-info/requires.txt
indra.util.egg-info/top_level.txt
indra.util.egg-info/zip-safe
indra/util/__init__.py
indra/util/fastest_elementtree.py
indra/util/helpformatter.py
indra/util/llmanifest.py
indra/util/llsubprocess.py
indra/util/llversion.py
indra/util/named_query.py
indra/util/shutil2.py
indra/util/term.py