Metadata-Version: 1.0
Name: indra.util
Version: 1.0
Summary: Utility functions for the indra library collection
Home-page: http://wiki.secondlife.com/wiki
Author: Linden Lab
Author-email: info@lindenlab.com
License: MIT License
Keywords: lindenlab secondlife ogp indra util
Platform: UNKNOWN
Classifier: Programming Language :: Python
Classifier: Topic :: Software Development :: Libraries :: Python Modules
